README
setup.py
src/spojcmd/__init__.py
src/spojcmd/main.py
src/spojcmd/settings.py
src/spojcmd/utils.py
src/spojcmd.egg-info/PKG-INFO
src/spojcmd.egg-info/SOURCES.txt
src/spojcmd.egg-info/dependency_links.txt
src/spojcmd.egg-info/entry_points.txt
src/spojcmd.egg-info/not-zip-safe
src/spojcmd.egg-info/requires.txt
src/spojcmd.egg-info/top_level.txt
src/spojcmd/commands/__init__.py
src/spojcmd/commands/auth.py
src/spojcmd/commands/desc.py
src/spojcmd/commands/list.py
src/spojcmd/commands/status.py
src/spojcmd/commands/tackle.py