Metadata-Version: 1.1
Name: spojcmd
Version: 0.3
Summary: command line tool for spoj.com 
Home-page: http://github.com/tvanicraath/spojcmd
Author: Rachit Nimavat
Author-email: iamrachiit@gmail.com
License: BSD
Keywords: spoj problems command line algorithmic problems
Platform: UNKNOWN
Classifier: Development Status :: 3 - Alpha
Classifier: Topic :: Utilities
Classifier: Topic :: Education
Classifier: Intended Audience :: Customer Service
